[
  {
    "symbolInput": "FTSE:FSI",
    "basic": {
      "symbol": "FTSE:FSI",
      "name": "FTSE 100 Index",
      "exchange": "FTSE International",
      "exhangeCode": "FSI",
      "bridgeExchangeCode": "GBFT",
      "currency": "GBP"
    },
    "quote": {
      "lastPrice": 7489.21,
      "openPrice": 7486.67,
      "high": 7496.8,
      "low": 7420,
      "previousClosePrice": 7486.67,
      "change1Day": 2.5399999999999636,
      "change1DayPercent": 0.033926966194582686,
      "change1Week": 112.35999999999967,
      "change1WeekPercent": 1.5231433470925893,
      "timeStamp": "2022-11-28T16:12:02",
      "volume": 359377280
    }
  },
  {
    "symbolInput": "INX:IOM",
    "basic": {
      "symbol": "INX:IOM",
      "name": "S&P 500 INDEX",
      "exchange": "CME:Index and Options Market",
      "exhangeCode": "IOM",
      "bridgeExchangeCode": "USCO",
      "currency": "USD"
    },
    "quote": {
      "lastPrice": 3991.82,
      "openPrice": 4005.36,
      "high": 4012.27,
      "low": 3987.27,
      "closePrice": 4026.12,
      "previousClosePrice": 4026.12,
      "change1Day": -34.29999999999973,
      "change1DayPercent": -0.8519368523541208,
      "change1Week": 41.88000000000011,
      "change1WeekPercent": 1.0602692699129634,
      "ask": 3992.64,
      "bid": 3990.96,
      "timeStamp": "2022-11-28T16:17:02",
      "volume": 580193000
    }
  },
  {
    "symbolInput": "EURUSD",
    "basic": {
      "symbol": "EURUSD",
      "name": "Euro/US Dollar FX Spot Rate",
      "exchange": "SOURCE IS A THOMSON REUTERS CONTRIBUTOR",
      "exhangeCode": "RCT",
      "bridgeExchangeCode": "CUX"
    },
    "quote": {
      "lastPrice": 1.0403,
      "openPrice": 1.0388,
      "high": 1.0496,
      "low": 1.0342,
      "closePrice": 1.0395,
      "previousClosePrice": 1.0395,
      "change1Day": 0.0007999999999999119,
      "change1DayPercent": 0.07696007696006847,
      "change1Week": 0.016000000000000014,
      "change1WeekPercent": 1.5620423703992985,
      "ask": 1.0409000000000002,
      "bid": 1.0403,
      "timeStamp": "2022-11-28T15:49:00",
      "volume": 0
    }
  },
  {
    "symbolInput": "GBPUSD",
    "basic": {
      "symbol": "GBPUSD",
      "name": "UK Pound Sterling/US Dollar FX Spot Rate",
      "exchange": "SOURCE IS A THOMSON REUTERS CONTRIBUTOR",
      "exhangeCode": "RCT",
      "bridgeExchangeCode": "CUX"
    },
    "quote": {
      "lastPrice": 1.2051,
      "openPrice": 1.2075,
      "high": 1.2118,
      "low": 1.2027,
      "closePrice": 1.2093,
      "previousClosePrice": 1.2093,
      "change1Day": -0.0041999999999999815,
      "change1DayPercent": -0.34730836020838346,
      "change1Week": 0.022750000000000048,
      "change1WeekPercent": 1.9241341396371674,
      "ask": 1.2055,
      "bid": 1.2051,
      "timeStamp": "2022-11-28T15:50:00",
      "volume": 0
    }
  },
  {
    "symbolInput": "IB.1:IEU",
    "basic": {
      "symbol": "IB.1:IEU",
      "name": "ICE Brent Crude Oil Front Month",
      "exchange": "Intercontinental Exchange Europe",
      "exhangeCode": "IEU",
      "bridgeExchangeCode": "FTIE",
      "currency": "USD"
    },
    "quote": {
      "lastPrice": 82.33,
      "openPrice": 83.58,
      "high": 83.93,
      "low": 80.61,
      "closePrice": 83.63,
      "previousClosePrice": 83.63,
      "change1Day": -1.2999999999999972,
      "change1DayPercent": -1.5544661006815703,
      "change1Week": -5.460000000000008,
      "change1WeekPercent": -6.219387173937815,
      "ask": 82.36,
      "askSize": 8,
      "bid": 82.33,
      "bidSize": 1,
      "timeStamp": "2022-11-28T16:17:02",
      "volume": 62370
    }
  },
  {
    "symbolInput": "JPMUS10YCMY:REU",
    "basic": {
      "symbol": "JPMUS10YCMY:REU",
      "name": "US 10YR",
      "exchange": "Thomson Reuters",
      "exhangeCode": "REU",
      "bridgeExchangeCode": "XXBR"
    },
    "quote": {
      "lastPrice": 3.703,
      "openPrice": 3.703,
      "high": 3.703,
      "low": 3.703,
      "previousClosePrice": 3.694,
      "change1Day": 0.008999999999999897,
      "change1DayPercent": 0.24363833243096636,
      "change1Week": -0.13500000000000023,
      "change1WeekPercent": -3.5174570088587864,
      "timeStamp": "2022-11-25T05:00:00",
      "volume": 0
    }
  }
]
