[
  {
    "symbolInput": "FTSE:FSI",
    "basic": {
      "symbol": "FTSE:FSI",
      "name": "FTSE 100 Index",
      "exchange": "FTSE International",
      "exhangeCode": "FSI",
      "bridgeExchangeCode": "GBFT",
      "currency": "GBP"
    },
    "quote": {
      "lastPrice": 7073.6900000000005,
      "openPrice": 7056.07,
      "high": 7093.05,
      "low": 7034.24,
      "previousClosePrice": 7056.07,
      "change1Day": 17.6200000000008,
      "change1DayPercent": 0.24971407596581102,
      "change1Week": 129.78000000000065,
      "change1WeekPercent": 1.8689758363803772,
      "timeStamp": "2022-10-27T15:35:30",
      "volume": 920365084
    }
  },
  {
    "symbolInput": "INX:IOM",
    "basic": {
      "symbol": "INX:IOM",
      "name": "S&P 500 INDEX",
      "exchange": "CME:Index and Options Market",
      "exhangeCode": "IOM",
      "bridgeExchangeCode": "USCO",
      "currency": "USD"
    },
    "quote": {
      "lastPrice": 3807.3,
      "openPrice": 3834.69,
      "high": 3859.9500000000003,
      "low": 3803.79,
      "closePrice": 3807.3,
      "previousClosePrice": 3830.6,
      "change1Day": -23.299999999999727,
      "change1DayPercent": -0.6082598026418766,
      "change1Week": 141.51999999999998,
      "change1WeekPercent": 3.860569919635111,
      "ask": 3844.7000000000003,
      "bid": 3710.77,
      "timeStamp": "2022-10-27T21:07:57",
      "volume": 3065025000
    }
  },
  {
    "symbolInput": "EURUSD",
    "basic": {
      "symbol": "EURUSD",
      "name": "Euro/US Dollar FX Spot Rate",
      "exchange": "SOURCE IS A THOMSON REUTERS CONTRIBUTOR",
      "exhangeCode": "RCT",
      "bridgeExchangeCode": "CUX"
    },
    "quote": {
      "lastPrice": 0.9987,
      "openPrice": 0.9964000000000001,
      "high": 0.9997,
      "low": 0.9959,
      "closePrice": 0.9962000000000001,
      "previousClosePrice": 0.9962000000000001,
      "change1Day": 0.0024999999999999467,
      "change1DayPercent": 0.2509536237703219,
      "change1Week": 0.012500000000000067,
      "change1WeekPercent": 1.2674913810586157,
      "ask": 0.9991000000000001,
      "bid": 0.9987,
      "timeStamp": "2022-10-28T04:19:00",
      "volume": 0
    }
  },
  {
    "symbolInput": "GBPUSD",
    "basic": {
      "symbol": "GBPUSD",
      "name": "UK Pound Sterling/US Dollar FX Spot Rate",
      "exchange": "SOURCE IS A THOMSON REUTERS CONTRIBUTOR",
      "exhangeCode": "RCT",
      "bridgeExchangeCode": "CUX"
    },
    "quote": {
      "lastPrice": 1.1577,
      "openPrice": 1.1561000000000001,
      "high": 1.1594,
      "low": 1.1546,
      "closePrice": 1.1564,
      "previousClosePrice": 1.1564,
      "change1Day": 0.0012999999999998568,
      "change1DayPercent": 0.11241784849531794,
      "change1Week": 0.02729999999999988,
      "change1WeekPercent": 2.415074309978758,
      "ask": 1.1582000000000001,
      "bid": 1.1577,
      "timeStamp": "2022-10-28T04:20:00",
      "volume": 0
    }
  },
  {
    "symbolInput": "IB.1:IEU",
    "basic": {
      "symbol": "IB.1:IEU",
      "name": "ICE Brent Crude Oil Front Month",
      "exchange": "Intercontinental Exchange Europe",
      "exhangeCode": "IEU",
      "bridgeExchangeCode": "FTIE",
      "currency": "USD"
    },
    "quote": {
      "lastPrice": 96.27,
      "openPrice": 96.58,
      "high": 96.76,
      "low": 95.96000000000001,
      "closePrice": 96.96000000000001,
      "previousClosePrice": 96.96000000000001,
      "change1Day": -0.6900000000000119,
      "change1DayPercent": -0.7116336633663489,
      "change1Week": 2.6700000000000017,
      "change1WeekPercent": 2.8525641025641044,
      "ask": 96.31,
      "askSize": 4,
      "bid": 96.28,
      "bidSize": 3,
      "timeStamp": "2022-10-28T04:42:00",
      "volume": 3074
    }
  },
  {
    "symbolInput": "JPMUS10YCMY:REU",
    "basic": {
      "symbol": "JPMUS10YCMY:REU",
      "name": "US 10YR",
      "exchange": "Thomson Reuters",
      "exhangeCode": "REU",
      "bridgeExchangeCode": "XXBR"
    },
    "quote": {
      "lastPrice": 3.931,
      "openPrice": 3.931,
      "high": 3.931,
      "low": 3.931,
      "previousClosePrice": 4.011,
      "change1Day": -0.08000000000000007,
      "change1DayPercent": -1.9945150835203207,
      "change1Week": -0.28500000000000014,
      "change1WeekPercent": -6.759962049335867,
      "timeStamp": "2022-10-27T04:00:00",
      "volume": 0
    }
  }
]
