[
  {
    "symbolInput": "FTSE:FSI",
    "basic": {
      "symbol": "FTSE:FSI",
      "name": "FTSE 100 Index",
      "exchange": "FTSE International",
      "exhangeCode": "FSI",
      "bridgeExchangeCode": "GBFT",
      "currency": "GBP"
    },
    "quote": {
      "lastPrice": 7473.34,
      "openPrice": 7469.28,
      "high": 7496.400000000001,
      "low": 7462.8,
      "previousClosePrice": 7469.28,
      "change1Day": 4.0600000000004,
      "change1DayPercent": 0.054355975408612346,
      "change1Week": 141.22000000000025,
      "change1WeekPercent": 1.9260459457837604,
      "timeStamp": "2022-12-23T12:22:19",
      "volume": 91775428
    }
  },
  {
    "symbolInput": "INX:IOM",
    "basic": {
      "symbol": "INX:IOM",
      "name": "S&P 500 INDEX",
      "exchange": "CME:Index and Options Market",
      "exhangeCode": "IOM",
      "bridgeExchangeCode": "USCO",
      "currency": "USD"
    },
    "quote": {
      "lastPrice": 3822.39,
      "openPrice": 3853.26,
      "high": 3853.26,
      "low": 3764.4900000000002,
      "closePrice": 3822.39,
      "previousClosePrice": 3878.44,
      "change1Day": -56.05000000000018,
      "change1DayPercent": -1.4451686760656393,
      "change1Week": -73.36000000000013,
      "change1WeekPercent": -1.8830777128922576,
      "ask": 3841.1,
      "bid": 3795,
      "timeStamp": "2022-12-22T22:08:35",
      "volume": 2365339000
    }
  },
  {
    "symbolInput": "EURUSD",
    "basic": {
      "symbol": "EURUSD",
      "name": "Euro/US Dollar FX Spot Rate",
      "exchange": "SOURCE IS A THOMSON REUTERS CONTRIBUTOR",
      "exhangeCode": "RCT",
      "bridgeExchangeCode": "CUX"
    },
    "quote": {
      "lastPrice": 1.0613000000000001,
      "openPrice": 1.0594000000000001,
      "high": 1.063,
      "low": 1.0587,
      "closePrice": 1.0593000000000001,
      "previousClosePrice": 1.0593000000000001,
      "change1Day": 0.0020000000000000018,
      "change1DayPercent": 0.18880392712168428,
      "change1Week": 0.0029000000000001247,
      "change1WeekPercent": 0.27399848828421436,
      "ask": 1.0614000000000001,
      "bid": 1.0613000000000001,
      "timeStamp": "2022-12-23T12:00:00",
      "volume": 0
    }
  },
  {
    "symbolInput": "GBPUSD",
    "basic": {
      "symbol": "GBPUSD",
      "name": "UK Pound Sterling/US Dollar FX Spot Rate",
      "exchange": "SOURCE IS A THOMSON REUTERS CONTRIBUTOR",
      "exhangeCode": "RCT",
      "bridgeExchangeCode": "CUX"
    },
    "quote": {
      "lastPrice": 1.2067,
      "openPrice": 1.2043000000000001,
      "high": 1.209,
      "low": 1.202,
      "closePrice": 1.2043000000000001,
      "previousClosePrice": 1.2043000000000001,
      "change1Day": 0.0023999999999999577,
      "change1DayPercent": 0.1992858922195431,
      "change1Week": -0.007549999999999946,
      "change1WeekPercent": -0.6217829936174548,
      "ask": 1.2071,
      "bid": 1.2067,
      "timeStamp": "2022-12-23T12:00:00",
      "volume": 0
    }
  },
  {
    "symbolInput": "IB.1:IEU",
    "basic": {
      "symbol": "IB.1:IEU",
      "name": "ICE Brent Crude Oil Front Month",
      "exchange": "Intercontinental Exchange Europe",
      "exhangeCode": "IEU",
      "bridgeExchangeCode": "FTIE",
      "currency": "USD"
    },
    "quote": {
      "lastPrice": 82.89,
      "openPrice": 81.69,
      "high": 83.2,
      "low": 81.29,
      "closePrice": 80.98,
      "previousClosePrice": 80.98,
      "change1Day": 1.9099999999999966,
      "change1DayPercent": 2.358607063472458,
      "change1Week": 3.6299999999999955,
      "change1WeekPercent": 4.579863739591213,
      "ask": 82.89,
      "askSize": 17,
      "bid": 82.86,
      "bidSize": 2,
      "timeStamp": "2022-12-23T12:27:18",
      "volume": 40309
    }
  },
  {
    "symbolInput": "JPMUS10YCMY:REU",
    "basic": {
      "symbol": "JPMUS10YCMY:REU",
      "name": "US 10YR",
      "exchange": "Thomson Reuters",
      "exhangeCode": "REU",
      "bridgeExchangeCode": "XXBR"
    },
    "quote": {
      "lastPrice": 3.679,
      "openPrice": 3.679,
      "high": 3.679,
      "low": 3.679,
      "previousClosePrice": 3.673,
      "change1Day": 0.005999999999999783,
      "change1DayPercent": 0.16335420637080816,
      "change1Week": 0.19399999999999995,
      "change1WeekPercent": 5.566714490674317,
      "timeStamp": "2022-12-22T05:00:00",
      "volume": 0
    }
  }
]
