[
  {
    "symbolInput": "FTSE:FSI",
    "basic": {
      "symbol": "FTSE:FSI",
      "name": "FTSE 100 Index",
      "exchange": "FTSE International",
      "exhangeCode": "FSI",
      "bridgeExchangeCode": "GBFT",
      "currency": "GBP"
    },
    "quote": {
      "lastPrice": 7013.4800000000005,
      "openPrice": 7013.99,
      "high": 7025.22,
      "low": 6949.24,
      "previousClosePrice": 7013.99,
      "change1Day": -0.5099999999993088,
      "change1DayPercent": -0.007271182308490728,
      "change1Week": 76.74000000000069,
      "change1WeekPercent": 1.1062833550053872,
      "timeStamp": "2022-10-25T15:35:30",
      "volume": 621328938
    }
  },
  {
    "symbolInput": "INX:IOM",
    "basic": {
      "symbol": "INX:IOM",
      "name": "S&P 500 INDEX",
      "exchange": "CME:Index and Options Market",
      "exhangeCode": "IOM",
      "bridgeExchangeCode": "USCO",
      "currency": "USD"
    },
    "quote": {
      "lastPrice": 3859.11,
      "openPrice": 3799.44,
      "high": 3862.85,
      "low": 3799.44,
      "closePrice": 3859.11,
      "previousClosePrice": 3797.34,
      "change1Day": 61.76999999999998,
      "change1DayPercent": 1.6266649812763665,
      "change1Week": 139.1300000000001,
      "change1WeekPercent": 3.7400738713649027,
      "ask": 3890.44,
      "bid": 3780.4500000000003,
      "timeStamp": "2022-10-25T21:06:29",
      "volume": 2710890000
    }
  },
  {
    "symbolInput": "EURUSD",
    "basic": {
      "symbol": "EURUSD",
      "name": "Euro/US Dollar FX Spot Rate",
      "exchange": "SOURCE IS A THOMSON REUTERS CONTRIBUTOR",
      "exhangeCode": "RCT",
      "bridgeExchangeCode": "CUX"
    },
    "quote": {
      "lastPrice": 0.9959,
      "openPrice": 0.9962000000000001,
      "high": 0.9968,
      "low": 0.9956,
      "closePrice": 0.9963000000000001,
      "previousClosePrice": 0.9963000000000001,
      "change1Day": -0.00040000000000006697,
      "change1DayPercent": -0.04014854963365121,
      "change1Week": 0.010499999999999954,
      "change1WeekPercent": 1.0655571341587124,
      "ask": 0.9963000000000001,
      "bid": 0.9959,
      "timeStamp": "2022-10-25T22:19:00",
      "volume": 0
    }
  },
  {
    "symbolInput": "GBPUSD",
    "basic": {
      "symbol": "GBPUSD",
      "name": "UK Pound Sterling/US Dollar FX Spot Rate",
      "exchange": "SOURCE IS A THOMSON REUTERS CONTRIBUTOR",
      "exhangeCode": "RCT",
      "bridgeExchangeCode": "CUX"
    },
    "quote": {
      "lastPrice": 1.1462,
      "openPrice": 1.1474,
      "high": 1.1479000000000001,
      "low": 1.1457000000000002,
      "closePrice": 1.1467,
      "previousClosePrice": 1.1467,
      "change1Day": -0.0004999999999999449,
      "change1DayPercent": -0.04360338362256431,
      "change1Week": 0.014200000000000212,
      "change1WeekPercent": 1.254416961130761,
      "ask": 1.1465,
      "bid": 1.1462,
      "timeStamp": "2022-10-25T22:19:00",
      "volume": 0
    }
  },
  {
    "symbolInput": "IB.1:IEU",
    "basic": {
      "symbol": "IB.1:IEU",
      "name": "ICE Brent Crude Oil Front Month",
      "exchange": "Intercontinental Exchange Europe",
      "exhangeCode": "IEU",
      "bridgeExchangeCode": "FTIE",
      "currency": "USD"
    },
    "quote": {
      "lastPrice": 93.06,
      "openPrice": 93.47,
      "high": 94.38,
      "low": 91.62,
      "closePrice": 93.52,
      "previousClosePrice": 93.26,
      "change1Day": -0.20000000000000284,
      "change1DayPercent": -0.21445421402530862,
      "change1Week": 2.4200000000000017,
      "change1WeekPercent": 2.669902912621361,
      "ask": 93.16,
      "askSize": 1,
      "bid": 93.05,
      "bidSize": 2,
      "timeStamp": "2022-10-25T21:59:55",
      "volume": 160601
    }
  },
  {
    "symbolInput": "JPMUS10YCMY:REU",
    "basic": {
      "symbol": "JPMUS10YCMY:REU",
      "name": "US 10YR",
      "exchange": "Thomson Reuters",
      "exhangeCode": "REU",
      "bridgeExchangeCode": "XXBR"
    },
    "quote": {
      "lastPrice": 4.245,
      "openPrice": 4.245,
      "high": 4.245,
      "low": 4.245,
      "previousClosePrice": 4.216,
      "change1Day": 0.028999999999999915,
      "change1DayPercent": 0.6878557874762787,
      "change1Week": 0.2509999999999999,
      "change1WeekPercent": 6.2844266399599364,
      "timeStamp": "2022-10-24T04:00:00",
      "volume": 0
    }
  }
]
