[
  {
    "symbolInput": "FTSE:FSI",
    "basic": {
      "symbol": "FTSE:FSI",
      "name": "FTSE 100 Index",
      "exchange": "FTSE International",
      "exhangeCode": "FSI",
      "bridgeExchangeCode": "GBFT",
      "currency": "GBP"
    },
    "quote": {
      "lastPrice": 7299.99,
      "openPrice": 7334.84,
      "high": 7346.66,
      "low": 7288,
      "previousClosePrice": 7334.84,
      "change1Day": -34.850000000000364,
      "change1DayPercent": -0.4751296551799407,
      "change1Week": 205.46000000000004,
      "change1WeekPercent": 2.896033986747537,
      "timeStamp": "2022-11-07T16:35:30",
      "volume": 718412917
    }
  },
  {
    "symbolInput": "INX:IOM",
    "basic": {
      "symbol": "INX:IOM",
      "name": "S&P 500 INDEX",
      "exchange": "CME:Index and Options Market",
      "exhangeCode": "IOM",
      "bridgeExchangeCode": "USCO",
      "currency": "USD"
    },
    "quote": {
      "lastPrice": 3810.83,
      "openPrice": 3780.71,
      "high": 3811.16,
      "low": 3764.7000000000003,
      "closePrice": 3770.55,
      "previousClosePrice": 3770.55,
      "change1Day": 40.279999999999745,
      "change1DayPercent": 1.068279163517252,
      "change1Week": -61.15000000000009,
      "change1WeekPercent": -1.5792953475999383,
      "ask": 3811.4500000000003,
      "bid": 3810.3,
      "timeStamp": "2022-11-07T20:18:14",
      "volume": 1724296000
    }
  },
  {
    "symbolInput": "EURUSD",
    "basic": {
      "symbol": "EURUSD",
      "name": "Euro/US Dollar FX Spot Rate",
      "exchange": "SOURCE IS A THOMSON REUTERS CONTRIBUTOR",
      "exhangeCode": "RCT",
      "bridgeExchangeCode": "CUX"
    },
    "quote": {
      "lastPrice": 1.0027000000000001,
      "openPrice": 0.9905,
      "high": 1.0034,
      "low": 0.9908,
      "closePrice": 0.996,
      "previousClosePrice": 0.996,
      "change1Day": 0.00670000000000015,
      "change1DayPercent": 0.672690763052224,
      "change1Week": 0.014200000000000101,
      "change1WeekPercent": 1.4365199797673345,
      "ask": 1.0031,
      "bid": 1.0027000000000001,
      "timeStamp": "2022-11-07T19:49:00",
      "volume": 0
    }
  },
  {
    "symbolInput": "GBPUSD",
    "basic": {
      "symbol": "GBPUSD",
      "name": "UK Pound Sterling/US Dollar FX Spot Rate",
      "exchange": "SOURCE IS A THOMSON REUTERS CONTRIBUTOR",
      "exhangeCode": "RCT",
      "bridgeExchangeCode": "CUX"
    },
    "quote": {
      "lastPrice": 1.1537,
      "openPrice": 1.1301,
      "high": 1.1541000000000001,
      "low": 1.1291,
      "closePrice": 1.1375,
      "previousClosePrice": 1.1375,
      "change1Day": 0.016199999999999992,
      "change1DayPercent": 1.4241758241758236,
      "change1Week": 0.006650000000000045,
      "change1WeekPercent": 0.5797480493439733,
      "ask": 1.1541000000000001,
      "bid": 1.1537,
      "timeStamp": "2022-11-07T19:50:00",
      "volume": 0
    }
  },
  {
    "symbolInput": "IB.1:IEU",
    "basic": {
      "symbol": "IB.1:IEU",
      "name": "ICE Brent Crude Oil Front Month",
      "exchange": "Intercontinental Exchange Europe",
      "exhangeCode": "IEU",
      "bridgeExchangeCode": "FTIE",
      "currency": "USD"
    },
    "quote": {
      "lastPrice": 98.13,
      "openPrice": 97.31,
      "high": 99.56,
      "low": 96.5,
      "closePrice": 97.92,
      "previousClosePrice": 98.57000000000001,
      "change1Day": -0.44000000000001194,
      "change1DayPercent": -0.4463832809171268,
      "change1Week": 3.280000000000001,
      "change1WeekPercent": 3.458091723774382,
      "ask": 98.13,
      "askSize": 1,
      "bid": 98.12,
      "bidSize": 2,
      "timeStamp": "2022-11-07T20:18:05",
      "volume": 231728
    }
  },
  {
    "symbolInput": "JPMUS10YCMY:REU",
    "basic": {
      "symbol": "JPMUS10YCMY:REU",
      "name": "US 10YR",
      "exchange": "Thomson Reuters",
      "exhangeCode": "REU",
      "bridgeExchangeCode": "XXBR"
    },
    "quote": {
      "lastPrice": 4.171,
      "openPrice": 4.171,
      "high": 4.171,
      "low": 4.171,
      "previousClosePrice": 4.139,
      "change1Day": 0.03200000000000003,
      "change1DayPercent": 0.7731336071514865,
      "change1Week": 0.12700000000000067,
      "change1WeekPercent": 3.1404549950544185,
      "timeStamp": "2022-11-04T05:00:00",
      "volume": 0
    }
  }
]
