[
  {
    "symbolInput": "FTSE:FSI",
    "basic": {
      "symbol": "FTSE:FSI",
      "name": "FTSE 100 Index",
      "exchange": "FTSE International",
      "exhangeCode": "FSI",
      "bridgeExchangeCode": "GBFT",
      "currency": "GBP"
    },
    "quote": {
      "lastPrice": 7013.99,
      "openPrice": 6969.7300000000005,
      "high": 7047.37,
      "low": 6914.66,
      "previousClosePrice": 6969.7300000000005,
      "change1Day": 44.25999999999931,
      "change1DayPercent": 0.6350317731102827,
      "change1Week": 93.75,
      "change1WeekPercent": 1.3547218015560154,
      "timeStamp": "2022-10-24T15:35:30",
      "volume": 620033905
    }
  },
  {
    "symbolInput": "INX:IOM",
    "basic": {
      "symbol": "INX:IOM",
      "name": "S&P 500 INDEX",
      "exchange": "CME:Index and Options Market",
      "exhangeCode": "IOM",
      "bridgeExchangeCode": "USCO",
      "currency": "USD"
    },
    "quote": {
      "lastPrice": 3800.6800000000003,
      "openPrice": 3762.01,
      "high": 3810.7400000000002,
      "low": 3741.65,
      "closePrice": 3752.75,
      "previousClosePrice": 3752.75,
      "change1Day": 47.93000000000029,
      "change1DayPercent": 1.2771967224035785,
      "change1Week": 122.73000000000047,
      "change1WeekPercent": 3.336913226117823,
      "ask": 3801.23,
      "bid": 3800.23,
      "timeStamp": "2022-10-24T19:44:40",
      "volume": 1994175000
    }
  },
  {
    "symbolInput": "EURUSD",
    "basic": {
      "symbol": "EURUSD",
      "name": "Euro/US Dollar FX Spot Rate",
      "exchange": "SOURCE IS A THOMSON REUTERS CONTRIBUTOR",
      "exhangeCode": "RCT",
      "bridgeExchangeCode": "CUX"
    },
    "quote": {
      "lastPrice": 0.9878,
      "openPrice": 0.9856,
      "high": 0.9899,
      "low": 0.9808,
      "closePrice": 0.9860000000000001,
      "previousClosePrice": 0.9860000000000001,
      "change1Day": 0.0017999999999999128,
      "change1DayPercent": 0.18255578093305402,
      "change1Week": 0.0038000000000000256,
      "change1WeekPercent": 0.3861788617886205,
      "ask": 0.9882000000000001,
      "bid": 0.9878,
      "timeStamp": "2022-10-24T19:19:00",
      "volume": 0
    }
  },
  {
    "symbolInput": "GBPUSD",
    "basic": {
      "symbol": "GBPUSD",
      "name": "UK Pound Sterling/US Dollar FX Spot Rate",
      "exchange": "SOURCE IS A THOMSON REUTERS CONTRIBUTOR",
      "exhangeCode": "RCT",
      "bridgeExchangeCode": "CUX"
    },
    "quote": {
      "lastPrice": 1.129,
      "openPrice": 1.1354,
      "high": 1.1408,
      "low": 1.1259000000000001,
      "closePrice": 1.1302,
      "previousClosePrice": 1.1302,
      "change1Day": -0.0012000000000000899,
      "change1DayPercent": -0.1061758980711458,
      "change1Week": -0.006699999999999928,
      "change1WeekPercent": -0.5899445276041145,
      "ask": 1.1294,
      "bid": 1.129,
      "timeStamp": "2022-10-24T19:20:00",
      "volume": 0
    }
  },
  {
    "symbolInput": "IB.1:IEU",
    "basic": {
      "symbol": "IB.1:IEU",
      "name": "ICE Brent Crude Oil Front Month",
      "exchange": "Intercontinental Exchange Europe",
      "exhangeCode": "IEU",
      "bridgeExchangeCode": "FTIE",
      "currency": "USD"
    },
    "quote": {
      "lastPrice": 93.28,
      "openPrice": 93.59,
      "high": 94.4,
      "low": 91.22,
      "closePrice": 93.26,
      "previousClosePrice": 93.5,
      "change1Day": -0.21999999999999886,
      "change1DayPercent": -0.2352941176470576,
      "change1Week": 1.2999999999999972,
      "change1WeekPercent": 1.4133507284192184,
      "ask": 93.3,
      "askSize": 7,
      "bid": 93.27,
      "bidSize": 9,
      "timeStamp": "2022-10-24T19:44:12",
      "volume": 164049
    }
  },
  {
    "symbolInput": "JPMUS10YCMY:REU",
    "basic": {
      "symbol": "JPMUS10YCMY:REU",
      "name": "US 10YR",
      "exchange": "Thomson Reuters",
      "exhangeCode": "REU",
      "bridgeExchangeCode": "XXBR"
    },
    "quote": {
      "lastPrice": 4.216,
      "openPrice": 4.216,
      "high": 4.216,
      "low": 4.216,
      "previousClosePrice": 4.226,
      "change1Day": -0.009999999999999787,
      "change1DayPercent": -0.23663038334121597,
      "change1Week": 0.19500000000000028,
      "change1WeekPercent": 4.849539915443927,
      "timeStamp": "2022-10-21T04:00:00",
      "volume": 0
    }
  }
]
