[
  {
    "symbolInput": "FTSE:FSI",
    "basic": {
      "symbol": "FTSE:FSI",
      "name": "FTSE 100 Index",
      "exchange": "FTSE International",
      "exhangeCode": "FSI",
      "bridgeExchangeCode": "GBFT",
      "currency": "GBP"
    },
    "quote": {
      "lastPrice": 7011.33,
      "openPrice": 6920.24,
      "high": 7017.400000000001,
      "low": 6920.24,
      "previousClosePrice": 6920.24,
      "change1Day": 91.09000000000015,
      "change1DayPercent": 1.3162838283065348,
      "change1Week": 126.10000000000036,
      "change1WeekPercent": 1.831456610745035,
      "timeStamp": "2022-10-18T12:48:36",
      "volume": 256477331
    }
  },
  {
    "symbolInput": "INX:IOM",
    "basic": {
      "symbol": "INX:IOM",
      "name": "S&P 500 INDEX",
      "exchange": "CME:Index and Options Market",
      "exhangeCode": "IOM",
      "bridgeExchangeCode": "USCO",
      "currency": "USD"
    },
    "quote": {
      "lastPrice": 3677.9500000000003,
      "openPrice": 3638.65,
      "high": 3689.73,
      "low": 3638.65,
      "closePrice": 3677.9500000000003,
      "previousClosePrice": 3677.9500000000003,
      "change1Day": 94.87999999999965,
      "change1DayPercent": 2.6480085513260874,
      "change1Week": 65.5600000000004,
      "change1WeekPercent": 1.8148649509050907,
      "ask": 3793.98,
      "bid": 3718.21,
      "timeStamp": "2022-10-17T21:44:19",
      "volume": 2581606904000
    }
  },
  {
    "symbolInput": "EURUSD",
    "basic": {
      "symbol": "EURUSD",
      "name": "Euro/US Dollar FX Spot Rate",
      "exchange": "SOURCE IS A THOMSON REUTERS CONTRIBUTOR",
      "exhangeCode": "RCT",
      "bridgeExchangeCode": "CUX"
    },
    "quote": {
      "lastPrice": 0.9844,
      "openPrice": 0.9836,
      "high": 0.9873000000000001,
      "low": 0.9813000000000001,
      "closePrice": 0.9838,
      "previousClosePrice": 0.9838,
      "change1Day": 0.0006000000000000449,
      "change1DayPercent": 0.06098800569221843,
      "change1Week": 0.013900000000000023,
      "change1WeekPercent": 1.4322514167954685,
      "ask": 0.9848,
      "bid": 0.9844,
      "timeStamp": "2022-10-18T12:30:00",
      "volume": 0
    }
  },
  {
    "symbolInput": "GBPUSD",
    "basic": {
      "symbol": "GBPUSD",
      "name": "UK Pound Sterling/US Dollar FX Spot Rate",
      "exchange": "SOURCE IS A THOMSON REUTERS CONTRIBUTOR",
      "exhangeCode": "RCT",
      "bridgeExchangeCode": "CUX"
    },
    "quote": {
      "lastPrice": 1.1317000000000002,
      "openPrice": 1.1353,
      "high": 1.141,
      "low": 1.1256000000000002,
      "closePrice": 1.1353,
      "previousClosePrice": 1.1353,
      "change1Day": -0.0035999999999998256,
      "change1DayPercent": -0.317096802607225,
      "change1Week": 0.03500000000000014,
      "change1WeekPercent": 3.191392358894879,
      "ask": 1.1321,
      "bid": 1.1317000000000002,
      "timeStamp": "2022-10-18T12:30:00",
      "volume": 0
    }
  },
  {
    "symbolInput": "IB.1:IEU",
    "basic": {
      "symbol": "IB.1:IEU",
      "name": "ICE Brent Crude Oil Front Month",
      "exchange": "Intercontinental Exchange Europe",
      "exhangeCode": "IEU",
      "bridgeExchangeCode": "FTIE",
      "currency": "USD"
    },
    "quote": {
      "lastPrice": 91.47,
      "openPrice": 91.99,
      "high": 92.66,
      "low": 90.71000000000001,
      "closePrice": 91.62,
      "previousClosePrice": 91.62,
      "change1Day": -0.15000000000000568,
      "change1DayPercent": -0.16371971185331333,
      "change1Week": -2.3299999999999983,
      "change1WeekPercent": -2.4840085287846465,
      "ask": 91.46000000000001,
      "askSize": 1,
      "bid": 91.45,
      "bidSize": 2,
      "timeStamp": "2022-10-18T12:53:29",
      "volume": 102315
    }
  },
  {
    "symbolInput": "JPMUS10YCMY:REU",
    "basic": {
      "symbol": "JPMUS10YCMY:REU",
      "name": "US 10YR",
      "exchange": "Thomson Reuters",
      "exhangeCode": "REU",
      "bridgeExchangeCode": "XXBR"
    },
    "quote": {
      "lastPrice": 4.021,
      "openPrice": 4.021,
      "high": 4.021,
      "low": 4.021,
      "previousClosePrice": 4.012,
      "change1Day": 0.009000000000000341,
      "change1DayPercent": 0.224327018943179,
      "change1Week": 0.08299999999999974,
      "change1WeekPercent": 2.107668867445397,
      "timeStamp": "2022-10-17T04:00:00",
      "volume": 0
    }
  }
]
