[
  {
    "symbolInput": "FTSE:FSI",
    "basic": {
      "symbol": "FTSE:FSI",
      "name": "FTSE 100 Index",
      "exchange": "FTSE International",
      "exhangeCode": "FSI",
      "bridgeExchangeCode": "GBFT",
      "currency": "GBP"
    },
    "quote": {
      "lastPrice": 7296.25,
      "openPrice": 7306.14,
      "high": 7307.8,
      "low": 7263.46,
      "previousClosePrice": 7306.14,
      "change1Day": -9.890000000000327,
      "change1DayPercent": -0.13536559660778916,
      "change1Week": 152.10999999999967,
      "change1WeekPercent": 2.1291576032944435,
      "timeStamp": "2022-11-09T16:35:30",
      "volume": 529922731
    }
  },
  {
    "symbolInput": "INX:IOM",
    "basic": {
      "symbol": "INX:IOM",
      "name": "S&P 500 INDEX",
      "exchange": "CME:Index and Options Market",
      "exhangeCode": "IOM",
      "bridgeExchangeCode": "USCO",
      "currency": "USD"
    },
    "quote": {
      "lastPrice": 3748.57,
      "openPrice": 3810.94,
      "high": 3818.2000000000003,
      "low": 3744.2200000000003,
      "closePrice": 3748.57,
      "previousClosePrice": 3828.11,
      "change1Day": -79.53999999999996,
      "change1DayPercent": -2.077787733372342,
      "change1Week": -11.11999999999989,
      "change1WeekPercent": -0.2957690660666143,
      "ask": 3835.14,
      "bid": 3690.7400000000002,
      "timeStamp": "2022-11-09T22:03:53",
      "volume": 2542783000
    }
  },
  {
    "symbolInput": "EURUSD",
    "basic": {
      "symbol": "EURUSD",
      "name": "Euro/US Dollar FX Spot Rate",
      "exchange": "SOURCE IS A THOMSON REUTERS CONTRIBUTOR",
      "exhangeCode": "RCT",
      "bridgeExchangeCode": "CUX"
    },
    "quote": {
      "lastPrice": 1.0031,
      "openPrice": 1.0006000000000002,
      "high": 1.0042,
      "low": 1.0008000000000001,
      "closePrice": 1.0006000000000002,
      "previousClosePrice": 1.0006000000000002,
      "change1Day": 0.0024999999999999467,
      "change1DayPercent": 0.249850089946027,
      "change1Week": 0.027800000000000158,
      "change1WeekPercent": 2.850405003588656,
      "ask": 1.0032,
      "bid": 1.0031,
      "timeStamp": "2022-11-10T07:00:00",
      "volume": 0
    }
  },
  {
    "symbolInput": "GBPUSD",
    "basic": {
      "symbol": "GBPUSD",
      "name": "UK Pound Sterling/US Dollar FX Spot Rate",
      "exchange": "SOURCE IS A THOMSON REUTERS CONTRIBUTOR",
      "exhangeCode": "RCT",
      "bridgeExchangeCode": "CUX"
    },
    "quote": {
      "lastPrice": 1.1394,
      "openPrice": 1.1356000000000002,
      "high": 1.1413,
      "low": 1.1353,
      "closePrice": 1.1356000000000002,
      "previousClosePrice": 1.1356000000000002,
      "change1Day": 0.0037999999999998035,
      "change1DayPercent": 0.334624867911219,
      "change1Week": 0.022699999999999942,
      "change1WeekPercent": 2.0327751410405606,
      "ask": 1.1398000000000001,
      "bid": 1.1394,
      "timeStamp": "2022-11-10T07:00:00",
      "volume": 0
    }
  },
  {
    "symbolInput": "IB.1:IEU",
    "basic": {
      "symbol": "IB.1:IEU",
      "name": "ICE Brent Crude Oil Front Month",
      "exchange": "Intercontinental Exchange Europe",
      "exhangeCode": "IEU",
      "bridgeExchangeCode": "FTIE",
      "currency": "USD"
    },
    "quote": {
      "lastPrice": 92.33,
      "openPrice": 92.53,
      "high": 92.73,
      "low": 92.21000000000001,
      "closePrice": 92.65,
      "previousClosePrice": 92.65,
      "change1Day": -0.3200000000000074,
      "change1DayPercent": -0.3453858607663328,
      "change1Week": -2.219999999999999,
      "change1WeekPercent": -2.3479640401903743,
      "ask": 92.34,
      "askSize": 3,
      "bid": 92.32000000000001,
      "bidSize": 3,
      "timeStamp": "2022-11-10T07:25:46",
      "volume": 9810
    }
  },
  {
    "symbolInput": "JPMUS10YCMY:REU",
    "basic": {
      "symbol": "JPMUS10YCMY:REU",
      "name": "US 10YR",
      "exchange": "Thomson Reuters",
      "exhangeCode": "REU",
      "bridgeExchangeCode": "XXBR"
    },
    "quote": {
      "lastPrice": 4.101,
      "openPrice": 4.101,
      "high": 4.101,
      "low": 4.101,
      "previousClosePrice": 4.136,
      "change1Day": -0.03500000000000014,
      "change1DayPercent": -0.8462282398452645,
      "change1Week": -0.038000000000000256,
      "change1WeekPercent": -0.9180961584923956,
      "timeStamp": "2022-11-09T05:00:00",
      "volume": 0
    }
  }
]
