[
  {
    "symbolInput": "FTSE:FSI",
    "basic": {
      "symbol": "FTSE:FSI",
      "name": "FTSE 100 Index",
      "exchange": "FTSE International",
      "exhangeCode": "FSI",
      "bridgeExchangeCode": "GBFT",
      "currency": "GBP"
    },
    "quote": {
      "lastPrice": 7346.54,
      "openPrice": 7351.1900000000005,
      "high": 7354.07,
      "low": 7294.75,
      "previousClosePrice": 7351.1900000000005,
      "change1Day": -4.650000000000546,
      "change1DayPercent": -0.06325506482624643,
      "change1Week": -28.800000000000182,
      "change1WeekPercent": -0.3904904723036522,
      "timeStamp": "2022-11-17T16:35:30",
      "volume": 752043763
    }
  },
  {
    "symbolInput": "INX:IOM",
    "basic": {
      "symbol": "INX:IOM",
      "name": "S&P 500 INDEX",
      "exchange": "CME:Index and Options Market",
      "exhangeCode": "IOM",
      "bridgeExchangeCode": "USCO",
      "currency": "USD"
    },
    "quote": {
      "lastPrice": 3946.56,
      "openPrice": 3919.26,
      "high": 3954.33,
      "low": 3906.54,
      "closePrice": 3946.56,
      "previousClosePrice": 3958.79,
      "change1Day": -12.230000000000018,
      "change1DayPercent": -0.308932779965596,
      "change1Week": -9.809999999999945,
      "change1WeekPercent": -0.24795456441131505,
      "ask": 4009.42,
      "bid": 3892.17,
      "timeStamp": "2022-11-17T22:13:41",
      "volume": 2196880000
    }
  },
  {
    "symbolInput": "EURUSD",
    "basic": {
      "symbol": "EURUSD",
      "name": "Euro/US Dollar FX Spot Rate",
      "exchange": "SOURCE IS A THOMSON REUTERS CONTRIBUTOR",
      "exhangeCode": "RCT",
      "bridgeExchangeCode": "CUX"
    },
    "quote": {
      "lastPrice": 1.0377,
      "openPrice": 1.036,
      "high": 1.0387,
      "low": 1.0358,
      "closePrice": 1.036,
      "previousClosePrice": 1.036,
      "change1Day": 0.0017000000000000348,
      "change1DayPercent": 0.16409266409266746,
      "change1Week": 0.0022999999999999687,
      "change1WeekPercent": 0.22213637241645437,
      "ask": 1.0388,
      "bid": 1.0377,
      "timeStamp": "2022-11-18T04:00:00",
      "volume": 0
    }
  },
  {
    "symbolInput": "GBPUSD",
    "basic": {
      "symbol": "GBPUSD",
      "name": "UK Pound Sterling/US Dollar FX Spot Rate",
      "exchange": "SOURCE IS A THOMSON REUTERS CONTRIBUTOR",
      "exhangeCode": "RCT",
      "bridgeExchangeCode": "CUX"
    },
    "quote": {
      "lastPrice": 1.1919,
      "openPrice": 1.1862000000000001,
      "high": 1.1926,
      "low": 1.1859,
      "closePrice": 1.1862000000000001,
      "previousClosePrice": 1.1862000000000001,
      "change1Day": 0.005699999999999816,
      "change1DayPercent": 0.4805260495700401,
      "change1Week": 0.008199999999999985,
      "change1WeekPercent": 0.6927430936892781,
      "ask": 1.192,
      "bid": 1.1919,
      "timeStamp": "2022-11-18T04:00:00",
      "volume": 0
    }
  },
  {
    "symbolInput": "IB.1:IEU",
    "basic": {
      "symbol": "IB.1:IEU",
      "name": "ICE Brent Crude Oil Front Month",
      "exchange": "Intercontinental Exchange Europe",
      "exhangeCode": "IEU",
      "bridgeExchangeCode": "FTIE",
      "currency": "USD"
    },
    "quote": {
      "lastPrice": 90.58,
      "openPrice": 90.10000000000001,
      "high": 90.63,
      "low": 90.01,
      "closePrice": 89.78,
      "previousClosePrice": 89.78,
      "change1Day": 0.7999999999999972,
      "change1DayPercent": 0.8910670527957197,
      "change1Week": -5.180000000000007,
      "change1WeekPercent": -5.409356725146206,
      "ask": 90.59,
      "askSize": 164,
      "bid": 90.57000000000001,
      "bidSize": 2,
      "timeStamp": "2022-11-18T04:20:43",
      "volume": 4810
    }
  },
  {
    "symbolInput": "JPMUS10YCMY:REU",
    "basic": {
      "symbol": "JPMUS10YCMY:REU",
      "name": "US 10YR",
      "exchange": "Thomson Reuters",
      "exhangeCode": "REU",
      "bridgeExchangeCode": "XXBR"
    },
    "quote": {
      "lastPrice": 3.785,
      "openPrice": 3.785,
      "high": 3.785,
      "low": 3.785,
      "previousClosePrice": 3.694,
      "change1Day": 0.09100000000000019,
      "change1DayPercent": 2.46345425013536,
      "change1Week": -0.04499999999999993,
      "change1WeekPercent": -1.174934725848562,
      "timeStamp": "2022-11-17T05:00:00",
      "volume": 0
    }
  }
]
