[
  {
    "symbolInput": "FTSE:FSI",
    "basic": {
      "symbol": "FTSE:FSI",
      "name": "FTSE 100 Index",
      "exchange": "FTSE International",
      "exhangeCode": "FSI",
      "bridgeExchangeCode": "GBFT",
      "currency": "GBP"
    },
    "quote": {
      "lastPrice": 7376.85,
      "openPrice": 7385.52,
      "high": 7402.79,
      "low": 7343.37,
      "previousClosePrice": 7385.52,
      "change1Day": -8.670000000000073,
      "change1DayPercent": -0.11739186949598772,
      "change1Week": -8.319999999999709,
      "change1WeekPercent": -0.11265820556601552,
      "timeStamp": "2022-11-21T16:35:30",
      "volume": 630206595
    }
  },
  {
    "symbolInput": "INX:IOM",
    "basic": {
      "symbol": "INX:IOM",
      "name": "S&P 500 INDEX",
      "exchange": "CME:Index and Options Market",
      "exhangeCode": "IOM",
      "bridgeExchangeCode": "USCO",
      "currency": "USD"
    },
    "quote": {
      "lastPrice": 3943.06,
      "openPrice": 3956.23,
      "high": 3962,
      "low": 3933.34,
      "closePrice": 3965.34,
      "previousClosePrice": 3965.34,
      "change1Day": -22.2800000000002,
      "change1DayPercent": -0.5618685913440008,
      "change1Week": -14.190000000000055,
      "change1WeekPercent": -0.35858234885337176,
      "ask": 3943.83,
      "bid": 3942.11,
      "timeStamp": "2022-11-21T17:14:56",
      "volume": 880943000
    }
  },
  {
    "symbolInput": "EURUSD",
    "basic": {
      "symbol": "EURUSD",
      "name": "Euro/US Dollar FX Spot Rate",
      "exchange": "SOURCE IS A THOMSON REUTERS CONTRIBUTOR",
      "exhangeCode": "RCT",
      "bridgeExchangeCode": "CUX"
    },
    "quote": {
      "lastPrice": 1.0237,
      "openPrice": 1.0315,
      "high": 1.0333,
      "low": 1.0227,
      "closePrice": 1.0319,
      "previousClosePrice": 1.0319,
      "change1Day": -0.008199999999999985,
      "change1DayPercent": -0.7946506444422894,
      "change1Week": -0.008999999999999897,
      "change1WeekPercent": -0.8715018882540813,
      "ask": 1.0241,
      "bid": 1.0237,
      "timeStamp": "2022-11-21T16:50:00",
      "volume": 0
    }
  },
  {
    "symbolInput": "GBPUSD",
    "basic": {
      "symbol": "GBPUSD",
      "name": "UK Pound Sterling/US Dollar FX Spot Rate",
      "exchange": "SOURCE IS A THOMSON REUTERS CONTRIBUTOR",
      "exhangeCode": "RCT",
      "bridgeExchangeCode": "CUX"
    },
    "quote": {
      "lastPrice": 1.1787,
      "openPrice": 1.1885000000000001,
      "high": 1.1901000000000002,
      "low": 1.1782000000000001,
      "closePrice": 1.1887,
      "previousClosePrice": 1.1887,
      "change1Day": -0.010000000000000009,
      "change1DayPercent": -0.8412551526878109,
      "change1Week": 0.0033000000000000806,
      "change1WeekPercent": 0.28075548749362605,
      "ask": 1.1791,
      "bid": 1.1787,
      "timeStamp": "2022-11-21T16:50:00",
      "volume": 0
    }
  },
  {
    "symbolInput": "IB.1:IEU",
    "basic": {
      "symbol": "IB.1:IEU",
      "name": "ICE Brent Crude Oil Front Month",
      "exchange": "Intercontinental Exchange Europe",
      "exhangeCode": "IEU",
      "bridgeExchangeCode": "FTIE",
      "currency": "USD"
    },
    "quote": {
      "lastPrice": 85.92,
      "openPrice": 87.74,
      "high": 87.98,
      "low": 82.31,
      "previousClosePrice": 87.62,
      "change1Day": -1.7000000000000028,
      "change1DayPercent": -1.9401963022141095,
      "change1Week": -6.579999999999998,
      "change1WeekPercent": -7.113513513513511,
      "ask": 85.94,
      "askSize": 5,
      "bid": 85.92,
      "bidSize": 4,
      "timeStamp": "2022-11-21T17:14:56",
      "volume": 279687
    }
  },
  {
    "symbolInput": "JPMUS10YCMY:REU",
    "basic": {
      "symbol": "JPMUS10YCMY:REU",
      "name": "US 10YR",
      "exchange": "Thomson Reuters",
      "exhangeCode": "REU",
      "bridgeExchangeCode": "XXBR"
    },
    "quote": {
      "lastPrice": 3.831,
      "openPrice": 3.831,
      "high": 3.831,
      "low": 3.831,
      "previousClosePrice": 3.785,
      "change1Day": 0.04599999999999982,
      "change1DayPercent": 1.2153236459709331,
      "change1Week": -0.052000000000000046,
      "change1WeekPercent": -1.3391707442698957,
      "timeStamp": "2022-11-18T05:00:00",
      "volume": 0
    }
  }
]
