[
  {
    "symbolInput": "FTSE:FSI",
    "basic": {
      "symbol": "FTSE:FSI",
      "name": "FTSE 100 Index",
      "exchange": "FTSE International",
      "exhangeCode": "FSI",
      "bridgeExchangeCode": "GBFT",
      "currency": "GBP"
    },
    "quote": {
      "lastPrice": 7566.9400000000005,
      "openPrice": 7554.09,
      "high": 7609.25,
      "low": 7545.18,
      "previousClosePrice": 7554.09,
      "change1Day": 12.850000000000364,
      "change1DayPercent": 0.17010652507450089,
      "change1Week": 69.75000000000091,
      "change1WeekPercent": 0.9303485705977962,
      "timeStamp": "2023-01-04T15:25:09",
      "volume": 369813135
    }
  },
  {
    "symbolInput": "INX:IOM",
    "basic": {
      "symbol": "INX:IOM",
      "name": "S&P 500 INDEX",
      "exchange": "CME:Index and Options Market",
      "exhangeCode": "IOM",
      "bridgeExchangeCode": "USCO",
      "currency": "USD"
    },
    "quote": {
      "lastPrice": 3830.38,
      "openPrice": 3840.36,
      "high": 3855.75,
      "low": 3815.77,
      "previousClosePrice": 3824.14,
      "change1Day": 6.2400000000002365,
      "change1DayPercent": 0.16317394237659283,
      "change1Week": 47.16000000000031,
      "change1WeekPercent": 1.2465571655891097,
      "ask": 3831.7400000000002,
      "bid": 3829.41,
      "timeStamp": "2023-01-04T15:30:10",
      "volume": 514268000
    }
  },
  {
    "symbolInput": "EURUSD",
    "basic": {
      "symbol": "EURUSD",
      "name": "Euro/US Dollar FX Spot Rate",
      "exchange": "SOURCE IS A THOMSON REUTERS CONTRIBUTOR",
      "exhangeCode": "RCT",
      "bridgeExchangeCode": "CUX"
    },
    "quote": {
      "lastPrice": 1.0591000000000002,
      "openPrice": 1.0551000000000001,
      "high": 1.0635000000000001,
      "low": 1.0542,
      "closePrice": 1.0546,
      "previousClosePrice": 1.0546,
      "change1Day": 0.0045000000000001705,
      "change1DayPercent": 0.4267020671344747,
      "change1Week": -0.0018999999999997907,
      "change1WeekPercent": -0.17907634307255332,
      "ask": 1.0595,
      "bid": 1.0591000000000002,
      "timeStamp": "2023-01-04T15:10:00",
      "volume": 0
    }
  },
  {
    "symbolInput": "GBPUSD",
    "basic": {
      "symbol": "GBPUSD",
      "name": "UK Pound Sterling/US Dollar FX Spot Rate",
      "exchange": "SOURCE IS A THOMSON REUTERS CONTRIBUTOR",
      "exhangeCode": "RCT",
      "bridgeExchangeCode": "CUX"
    },
    "quote": {
      "lastPrice": 1.2021000000000002,
      "openPrice": 1.1966,
      "high": 1.2087,
      "low": 1.1956,
      "closePrice": 1.1966,
      "previousClosePrice": 1.1966,
      "change1Day": 0.00550000000000006,
      "change1DayPercent": 0.45963563429718035,
      "change1Week": 0.000600000000000156,
      "change1WeekPercent": 0.04993757802747865,
      "ask": 1.2025000000000001,
      "bid": 1.2021000000000002,
      "timeStamp": "2023-01-04T15:10:00",
      "volume": 0
    }
  },
  {
    "symbolInput": "IB.1:IEU",
    "basic": {
      "symbol": "IB.1:IEU",
      "name": "ICE Brent Crude Oil Front Month",
      "exchange": "Intercontinental Exchange Europe",
      "exhangeCode": "IEU",
      "bridgeExchangeCode": "FTIE",
      "currency": "USD"
    },
    "quote": {
      "lastPrice": 78.82000000000001,
      "openPrice": 82.31,
      "high": 82.72,
      "low": 78.5,
      "closePrice": 82.10000000000001,
      "previousClosePrice": 82.10000000000001,
      "change1Day": -3.280000000000001,
      "change1DayPercent": -3.9951278928136427,
      "change1Week": -4.289999999999992,
      "change1WeekPercent": -5.161833714354461,
      "ask": 78.83,
      "askSize": 11,
      "bid": 78.81,
      "bidSize": 7,
      "timeStamp": "2023-01-04T15:30:09",
      "volume": 183815
    }
  },
  {
    "symbolInput": "JPMUS10YCMY:REU",
    "basic": {
      "symbol": "JPMUS10YCMY:REU",
      "name": "US 10YR",
      "exchange": "Thomson Reuters",
      "exhangeCode": "REU",
      "bridgeExchangeCode": "XXBR"
    },
    "quote": {
      "lastPrice": 3.775,
      "openPrice": 3.775,
      "high": 3.775,
      "low": 3.775,
      "previousClosePrice": 3.876,
      "change1Day": -0.10099999999999998,
      "change1DayPercent": -2.6057791537667696,
      "change1Week": -0.10199999999999987,
      "change1WeekPercent": -2.63090018055197,
      "timeStamp": "2023-01-03T05:00:00",
      "volume": 0
    }
  }
]
