[
  {
    "symbolInput": "FTSE:FSI",
    "basic": {
      "symbol": "FTSE:FSI",
      "name": "FTSE 100 Index",
      "exchange": "FTSE International",
      "exhangeCode": "FSI",
      "bridgeExchangeCode": "GBFT",
      "currency": "GBP"
    },
    "quote": {
      "lastPrice": 7304.74,
      "openPrice": 7299.99,
      "high": 7305.92,
      "low": 7244.83,
      "previousClosePrice": 7299.99,
      "change1Day": 4.75,
      "change1DayPercent": 0.06506858228572916,
      "change1Week": 118.57999999999993,
      "change1WeekPercent": 1.6501163347323178,
      "timeStamp": "2022-11-08T13:35:04",
      "volume": 204987165
    }
  },
  {
    "symbolInput": "INX:IOM",
    "basic": {
      "symbol": "INX:IOM",
      "name": "S&P 500 INDEX",
      "exchange": "CME:Index and Options Market",
      "exhangeCode": "IOM",
      "bridgeExchangeCode": "USCO",
      "currency": "USD"
    },
    "quote": {
      "lastPrice": 3806.8,
      "openPrice": 3780.71,
      "high": 3813.95,
      "low": 3764.7,
      "closePrice": 3806.8,
      "previousClosePrice": 3806.8,
      "change1Day": 36.25,
      "change1DayPercent": 0.9613982045059739,
      "change1Week": -65.17999999999984,
      "change1WeekPercent": -1.6833764637213993,
      "ask": 3845.75,
      "bid": 3787.81,
      "timeStamp": "2022-11-07T22:14:03",
      "volume": 2496452846000
    }
  },
  {
    "symbolInput": "EURUSD",
    "basic": {
      "symbol": "EURUSD",
      "name": "Euro/US Dollar FX Spot Rate",
      "exchange": "SOURCE IS A THOMSON REUTERS CONTRIBUTOR",
      "exhangeCode": "RCT",
      "bridgeExchangeCode": "CUX"
    },
    "quote": {
      "lastPrice": 0.9995,
      "openPrice": 1.002,
      "high": 1.0031,
      "low": 0.9973000000000001,
      "closePrice": 1.0019,
      "previousClosePrice": 1.0019,
      "change1Day": -0.0023999999999999577,
      "change1DayPercent": -0.23954486475695755,
      "change1Week": 0.012050000000000005,
      "change1WeekPercent": 1.2203149526558312,
      "ask": 0.9998,
      "bid": 0.9995,
      "timeStamp": "2022-11-08T13:20:00",
      "volume": 0
    }
  },
  {
    "symbolInput": "GBPUSD",
    "basic": {
      "symbol": "GBPUSD",
      "name": "UK Pound Sterling/US Dollar FX Spot Rate",
      "exchange": "SOURCE IS A THOMSON REUTERS CONTRIBUTOR",
      "exhangeCode": "RCT",
      "bridgeExchangeCode": "CUX"
    },
    "quote": {
      "lastPrice": 1.1442,
      "openPrice": 1.1511,
      "high": 1.1536,
      "low": 1.1434,
      "closePrice": 1.1511,
      "previousClosePrice": 1.1511,
      "change1Day": -0.006899999999999906,
      "change1DayPercent": -0.5994266353922254,
      "change1Week": -0.0042999999999999705,
      "change1WeekPercent": -0.3744013931214602,
      "ask": 1.1443,
      "bid": 1.1442,
      "timeStamp": "2022-11-08T13:20:00",
      "volume": 0
    }
  },
  {
    "symbolInput": "IB.1:IEU",
    "basic": {
      "symbol": "IB.1:IEU",
      "name": "ICE Brent Crude Oil Front Month",
      "exchange": "Intercontinental Exchange Europe",
      "exhangeCode": "IEU",
      "bridgeExchangeCode": "FTIE",
      "currency": "USD"
    },
    "quote": {
      "lastPrice": 97.56,
      "openPrice": 98.24000000000001,
      "high": 98.3,
      "low": 96.76,
      "closePrice": 97.92,
      "previousClosePrice": 97.92,
      "change1Day": -0.35999999999999943,
      "change1DayPercent": -0.3676470588235288,
      "change1Week": 2.7900000000000063,
      "change1WeekPercent": 2.943969610636284,
      "ask": 97.57000000000001,
      "askSize": 2,
      "bid": 97.56,
      "bidSize": 3,
      "timeStamp": "2022-11-08T13:39:59",
      "volume": 97115
    }
  },
  {
    "symbolInput": "JPMUS10YCMY:REU",
    "basic": {
      "symbol": "JPMUS10YCMY:REU",
      "name": "US 10YR",
      "exchange": "Thomson Reuters",
      "exhangeCode": "REU",
      "bridgeExchangeCode": "XXBR"
    },
    "quote": {
      "lastPrice": 4.22,
      "openPrice": 4.22,
      "high": 4.22,
      "low": 4.22,
      "previousClosePrice": 4.171,
      "change1Day": 0.04899999999999949,
      "change1DayPercent": 1.1747782306401218,
      "change1Week": 0.1739999999999995,
      "change1WeekPercent": 4.300543746910516,
      "timeStamp": "2022-11-07T05:00:00",
      "volume": 0
    }
  }
]
