[
  {
    "symbolInput": "FTSE:FSI",
    "basic": {
      "symbol": "FTSE:FSI",
      "name": "FTSE 100 Index",
      "exchange": "FTSE International",
      "exhangeCode": "FSI",
      "bridgeExchangeCode": "GBFT",
      "currency": "GBP"
    },
    "quote": {
      "lastPrice": 7489.1900000000005,
      "openPrice": 7521.39,
      "high": 7567.2300000000005,
      "low": 7489.1900000000005,
      "previousClosePrice": 7521.39,
      "change1Day": -32.19999999999982,
      "change1DayPercent": -0.4281123568914764,
      "change1Week": -83.85999999999967,
      "change1WeekPercent": -1.1073477660915967,
      "timeStamp": "2022-12-07T16:35:30",
      "volume": 727846116
    }
  },
  {
    "symbolInput": "INX:IOM",
    "basic": {
      "symbol": "INX:IOM",
      "name": "S&P 500 INDEX",
      "exchange": "CME:Index and Options Market",
      "exhangeCode": "IOM",
      "bridgeExchangeCode": "USCO",
      "currency": "USD"
    },
    "quote": {
      "lastPrice": 3933.92,
      "openPrice": 3933.28,
      "high": 3957.57,
      "low": 3922.6800000000003,
      "closePrice": 3933.92,
      "previousClosePrice": 3941.26,
      "change1Day": -7.3400000000001455,
      "change1DayPercent": -0.1862348589029941,
      "change1Week": -146.19000000000005,
      "change1WeekPercent": -3.582991635029449,
      "ask": 3959.56,
      "bid": 3908.82,
      "timeStamp": "2022-12-07T22:22:20",
      "volume": 2263753000
    }
  },
  {
    "symbolInput": "EURUSD",
    "basic": {
      "symbol": "EURUSD",
      "name": "Euro/US Dollar FX Spot Rate",
      "exchange": "SOURCE IS A THOMSON REUTERS CONTRIBUTOR",
      "exhangeCode": "RCT",
      "bridgeExchangeCode": "CUX"
    },
    "quote": {
      "lastPrice": 1.0502,
      "openPrice": 1.0504,
      "high": 1.0515,
      "low": 1.0496,
      "closePrice": 1.0505,
      "previousClosePrice": 1.0505,
      "change1Day": -0.00029999999999996696,
      "change1DayPercent": -0.028557829604946877,
      "change1Week": -0.0021999999999999797,
      "change1WeekPercent": -0.209045990117824,
      "ask": 1.0506,
      "bid": 1.0502,
      "timeStamp": "2022-12-08T02:49:00",
      "volume": 0
    }
  },
  {
    "symbolInput": "GBPUSD",
    "basic": {
      "symbol": "GBPUSD",
      "name": "UK Pound Sterling/US Dollar FX Spot Rate",
      "exchange": "SOURCE IS A THOMSON REUTERS CONTRIBUTOR",
      "exhangeCode": "RCT",
      "bridgeExchangeCode": "CUX"
    },
    "quote": {
      "lastPrice": 1.2186000000000001,
      "openPrice": 1.22,
      "high": 1.2213,
      "low": 1.2181,
      "closePrice": 1.2199,
      "previousClosePrice": 1.2199,
      "change1Day": -0.0012999999999998568,
      "change1DayPercent": -0.10656611197637977,
      "change1Week": -0.006899999999999906,
      "change1WeekPercent": -0.5630354957160266,
      "ask": 1.2194,
      "bid": 1.2186000000000001,
      "timeStamp": "2022-12-08T02:50:00",
      "volume": 0
    }
  },
  {
    "symbolInput": "IB.1:IEU",
    "basic": {
      "symbol": "IB.1:IEU",
      "name": "ICE Brent Crude Oil Front Month",
      "exchange": "Intercontinental Exchange Europe",
      "exhangeCode": "IEU",
      "bridgeExchangeCode": "FTIE",
      "currency": "USD"
    },
    "quote": {
      "lastPrice": 77.75,
      "openPrice": 77.46000000000001,
      "high": 77.9,
      "low": 77.34,
      "closePrice": 77.17,
      "previousClosePrice": 77.17,
      "change1Day": 0.5799999999999983,
      "change1DayPercent": 0.7515874044317717,
      "change1Week": -9.510000000000005,
      "change1WeekPercent": -10.898464359385748,
      "ask": 77.8,
      "askSize": 8,
      "bid": 77.77,
      "bidSize": 8,
      "timeStamp": "2022-12-08T03:13:00",
      "volume": 4078
    }
  },
  {
    "symbolInput": "JPMUS10YCMY:REU",
    "basic": {
      "symbol": "JPMUS10YCMY:REU",
      "name": "US 10YR",
      "exchange": "Thomson Reuters",
      "exhangeCode": "REU",
      "bridgeExchangeCode": "XXBR"
    },
    "quote": {
      "lastPrice": 3.409,
      "openPrice": 3.409,
      "high": 3.409,
      "low": 3.409,
      "previousClosePrice": 3.52,
      "change1Day": -0.11100000000000021,
      "change1DayPercent": -3.153409090909097,
      "change1Week": -0.22999999999999998,
      "change1WeekPercent": -6.320417697169552,
      "timeStamp": "2022-12-07T05:00:00",
      "volume": 0
    }
  }
]
